rolog/__init__.py
rolog/rodi.py
rolog/targets/__init__.py
rolog-1.0.2.dist-info/LICENSE
rolog-1.0.2.dist-info/METADATA
rolog-1.0.2.dist-info/WHEEL
rolog-1.0.2.dist-info/top_level.txt
rolog-1.0.2.dist-info/RECORD
