Metadata-Version: 2.1
Name: rolog
Version: 1.0.2
Summary: Async friendly logging classes for Python 3
Home-page: https://github.com/RobertoPrevato/rolog
Author: RobertoPrevato
Author-email: roberto.prevato@gmail.com
License: MIT
Keywords: logging async await
Platform: UNKNOWN
Classifier: Development Status :: 5 - Production/Stable
Classifier: License :: OSI Approved :: MIT License
Classifier: Programming Language :: Python :: 3
Classifier: Operating System :: OS Independent
